nti/__init__.py
nti/property/__init__.py
nti/property/configure.zcml
nti/property/dataurl.py
nti/property/meta.zcml
nti/property/property.py
nti/property/schema.py
nti/property/tunables.py
nti/property/urlproperty.py
nti/property/tests/__init__.py
nti/property/tests/test_dataurl.py
nti/property/tests/test_property.py
nti/property/tests/test_schema.py
nti/property/tests/test_tunables.py
nti/property/tests/test_urlproperty.py
nti_property-2.2.2.dist-info/licenses/AUTHORS
nti_property-2.2.2.dist-info/licenses/LICENSE
nti_property-2.2.2.dist-info/METADATA
nti_property-2.2.2.dist-info/WHEEL
nti_property-2.2.2.dist-info/top_level.txt
nti_property-2.2.2.dist-info/zip-safe
nti_property-2.2.2.dist-info/RECORD
