Metadata-Version: 2.4
Name: nti.property
Version: 2.2.2
Summary: NTI Property
Home-page: https://github.com/OpenNTI/nti.property
Author: Jason Madden
Author-email: jason@nextthought.com
License: Apache
Keywords: Property
Classifier: Intended Audience :: Developers
Classifier: Natural Language :: English
Classifier: Operating System :: OS Independent
Classifier: License :: OSI Approved :: Apache Software License
Classifier: Programming Language :: Python :: 3
Classifier: Programming Language :: Python :: 3 :: Only
Classifier: Programming Language :: Python :: 3.10
Classifier: Programming Language :: Python :: 3.11
Classifier: Programming Language :: Python :: 3.12
Classifier: Programming Language :: Python :: 3.13
Classifier: Programming Language :: Python :: 3.14
Classifier: Programming Language :: Python :: Implementation :: CPython
Classifier: Programming Language :: Python :: Implementation :: PyPy
Requires-Python: >=3.10
License-File: LICENSE
License-File: AUTHORS
Requires-Dist: zope.annotation
Requires-Dist: zope.cachedescriptors>=4.2
Requires-Dist: zope.component
Requires-Dist: zope.contenttype
Requires-Dist: zope.schema>=4.7.0
Requires-Dist: ZConfig
Provides-Extra: zodb
Requires-Dist: zope.file>=1.0; extra == "zodb"
Provides-Extra: test
Requires-Dist: nti.testing; extra == "test"
Requires-Dist: pyhamcrest; extra == "test"
Requires-Dist: zope.testrunner; extra == "test"
Provides-Extra: docs
Requires-Dist: Sphinx; extra == "docs"
Requires-Dist: repoze.sphinx.autointerface; extra == "docs"
Requires-Dist: furo; extra == "docs"
Requires-Dist: zope.file; extra == "docs"
Dynamic: author
Dynamic: author-email
Dynamic: classifier
Dynamic: description
Dynamic: home-page
Dynamic: keywords
Dynamic: license
Dynamic: license-file
Dynamic: provides-extra
Dynamic: requires-dist
Dynamic: requires-python
Dynamic: summary
